cz_conventional_plus/__init__.py
cz_conventional_plus-1.0.3.dist-info/METADATA
cz_conventional_plus-1.0.3.dist-info/WHEEL
cz_conventional_plus-1.0.3.dist-info/entry_points.txt
cz_conventional_plus-1.0.3.dist-info/licenses/LICENSE
cz_conventional_plus-1.0.3.dist-info/RECORD
